progb/__init__.py
progb/main.py
progb-0.0.7.dist-info/LICENSE
progb-0.0.7.dist-info/METADATA
progb-0.0.7.dist-info/WHEEL
progb-0.0.7.dist-info/top_level.txt
progb-0.0.7.dist-info/RECORD
