Metadata-Version: 2.1
Name: progb
Version: 0.0.7
Summary: A simple Python package to display progress bars on all operating systems
Author-email: Henry Cook <henryscookolaizola@gmail.com>
Project-URL: Homepage, https://github.com/HCook86/progb
Project-URL: Bug Tracker, https://github.com/HCook86/progb
Classifier: Programming Language :: Python :: 3
Classifier: Operating System :: OS Independent
Requires-Python: >=3.6
License-File: LICENSE
